_mysql_connector.cpython-310-darwin.so
mysql/__init__.py
mysql/ai/__init__.py
mysql/ai/genai/__init__.py
mysql/ai/genai/embedding.py
mysql/ai/genai/generation.py
mysql/ai/genai/vector_store.py
mysql/ai/ml/__init__.py
mysql/ai/ml/base.py
mysql/ai/ml/classifier.py
mysql/ai/ml/model.py
mysql/ai/ml/outlier.py
mysql/ai/ml/regressor.py
mysql/ai/ml/transformer.py
mysql/ai/utils/__init__.py
mysql/ai/utils/atomic_cursor.py
mysql/ai/utils/dependencies.py
mysql/ai/utils/utils.py
mysql/connector/__init__.py
mysql/connector/_decorating.py
mysql/connector/_scripting.py
mysql/connector/abstracts.py
mysql/connector/authentication.py
mysql/connector/charsets.py
mysql/connector/connection.py
mysql/connector/connection_cext.py
mysql/connector/constants.py
mysql/connector/conversion.py
mysql/connector/cursor.py
mysql/connector/cursor_cext.py
mysql/connector/custom_types.py
mysql/connector/dbapi.py
mysql/connector/errorcode.py
mysql/connector/errors.py
mysql/connector/logger.py
mysql/connector/network.py
mysql/connector/optionfiles.py
mysql/connector/pooling.py
mysql/connector/protocol.py
mysql/connector/py.typed
mysql/connector/tls_ciphers.py
mysql/connector/types.py
mysql/connector/utils.py
mysql/connector/version.py
mysql/connector/aio/__init__.py
mysql/connector/aio/_decorating.py
mysql/connector/aio/abstracts.py
mysql/connector/aio/authentication.py
mysql/connector/aio/charsets.py
mysql/connector/aio/connection.py
mysql/connector/aio/cursor.py
mysql/connector/aio/logger.py
mysql/connector/aio/network.py
mysql/connector/aio/pooling.py
mysql/connector/aio/protocol.py
mysql/connector/aio/utils.py
mysql/connector/aio/plugins/__init__.py
mysql/connector/aio/plugins/authentication_kerberos_client.py
mysql/connector/aio/plugins/authentication_ldap_sasl_client.py
mysql/connector/aio/plugins/authentication_oci_client.py
mysql/connector/aio/plugins/authentication_openid_connect_client.py
mysql/connector/aio/plugins/authentication_webauthn_client.py
mysql_connector_python-9.6.0.dist-info/LICENSE.txt
mysql_connector_python-9.6.0.dist-info/METADATA
mysql_connector_python-9.6.0.dist-info/WHEEL
mysql_connector_python-9.6.0.dist-info/top_level.txt
mysql_connector_python-9.6.0.dist-info/RECORD
