Metadata-Version: 2.1
Name: mysql-connector-python
Version: 9.6.0
Summary: A self-contained Python driver for communicating with MySQL servers, using an API that is compliant with the Python Database API Specification v2.0 (PEP 249).
Home-page: UNKNOWN
Author: Oracle and/or its affiliates
Author-email: 
License: GNU GPLv2 (with FOSS License Exception)
Project-URL: Homepage, https://dev.mysql.com/doc/connector-python/en/
Project-URL: Documentation, https://dev.mysql.com/doc/connector-python/en/
Project-URL: Downloads, https://dev.mysql.com/downloads/connector/python/
Project-URL: Release Notes, https://dev.mysql.com/doc/relnotes/connector-python/en/
Project-URL: Source Code, https://github.com/mysql/mysql-connector-python
Project-URL: Bug System, https://bugs.mysql.com/
Project-URL: Slack, https://mysqlcommunity.slack.com/messages/connectors
Project-URL: Forums, https://forums.mysql.com/list.php?50
Project-URL: Blog, https://blogs.oracle.com/mysql/
Keywords: mysql,database,db,connector,driver
Platform: UNKNOWN
Classifier: Development Status :: 5 - Production/Stable
Classifier: Intended Audience :: Developers
Classifier: Intended Audience :: Education
Classifier: License :: OSI Approved :: GNU General Public License (GPL)
Classifier: Operating System :: MacOS :: MacOS X
Classifier: Operating System :: Microsoft :: Windows
Classifier: Operating System :: POSIX :: Linux
Classifier: Operating System :: Unix
Classifier: Programming Language :: Python :: 3
Classifier: Programming Language :: Python :: 3.10
Classifier: Programming Language :: Python :: 3.11
Classifier: Programming Language :: Python :: 3.12
Classifier: Programming Language :: Python :: 3.13
Classifier: Programming Language :: Python :: 3.14
Classifier: Topic :: Database
Classifier: Topic :: Software Development
Classifier: Topic :: Software Development :: Libraries :: Python Modules
Classifier: Typing :: Typed
Requires-Python: >=3.10
License-File: LICENSE.txt
Provides-Extra: dns-srv
Requires-Dist: dnspython==2.6.1; extra == "dns-srv"
Provides-Extra: gssapi
Requires-Dist: gssapi==1.8.3; extra == "gssapi"
Provides-Extra: telemetry
Requires-Dist: opentelemetry-api==1.33.1; extra == "telemetry"
Requires-Dist: opentelemetry-sdk==1.33.1; extra == "telemetry"
Requires-Dist: opentelemetry-exporter-otlp-proto-http==1.33.1; extra == "telemetry"
Provides-Extra: webauthn
Requires-Dist: fido2==1.1.2; extra == "webauthn"
